[{"id":1, "superclassid":"56", "superclassname":"org.jhotdraw.beans.AbstractBean", "ownerclassid":"1", "ownerclassname":"org.jhotdraw.app.AbstractApplication"},
 {"id":2, "superclassid":"1", "superclassname":"org.jhotdraw.app.AbstractApplication", "ownerclassid":"5", "ownerclassname":"org.jhotdraw.app.DefaultAppletApplication"},
 {"id":3, "superclassid":"56", "superclassname":"org.jhotdraw.beans.AbstractBean", "ownerclassid":"6", "ownerclassname":"org.jhotdraw.app.DefaultApplicationModel"},
 {"id":4, "superclassid":"1", "superclassname":"org.jhotdraw.app.AbstractApplication", "ownerclassid":"7", "ownerclassname":"org.jhotdraw.app.DefaultMDIApplication"},
 {"id":5, "superclassid":"1", "superclassname":"org.jhotdraw.app.AbstractApplication", "ownerclassid":"8", "ownerclassname":"org.jhotdraw.app.DefaultOSXApplication"},
 {"id":6, "superclassid":"1", "superclassname":"org.jhotdraw.app.AbstractApplication", "ownerclassid":"9", "ownerclassname":"org.jhotdraw.app.DefaultSDIApplication"},
 {"id":7, "superclassid":"17", "superclassname":"org.jhotdraw.app.action.AbstractApplicationAction", "ownerclassid":"16", "ownerclassname":"org.jhotdraw.app.action.AboutAction"},
 {"id":8, "superclassid":"19", "superclassname":"org.jhotdraw.app.action.AbstractViewAction", "ownerclassid":"18", "ownerclassname":"org.jhotdraw.app.action.AbstractSaveBeforeAction"},
 {"id":9, "superclassid":"18", "superclassname":"org.jhotdraw.app.action.AbstractSaveBeforeAction", "ownerclassid":"22", "ownerclassname":"org.jhotdraw.app.action.ClearAction"},
 {"id":10, "superclassid":"17", "superclassname":"org.jhotdraw.app.action.AbstractApplicationAction", "ownerclassid":"23", "ownerclassname":"org.jhotdraw.app.action.ClearRecentFilesAction"},
 {"id":11, "superclassid":"18", "superclassname":"org.jhotdraw.app.action.AbstractSaveBeforeAction", "ownerclassid":"25", "ownerclassname":"org.jhotdraw.app.action.CloseAction"},
 {"id":12, "superclassid":"17", "superclassname":"org.jhotdraw.app.action.AbstractApplicationAction", "ownerclassid":"30", "ownerclassname":"org.jhotdraw.app.action.ExitAction"},
 {"id":13, "superclassid":"19", "superclassname":"org.jhotdraw.app.action.AbstractViewAction", "ownerclassid":"31", "ownerclassname":"org.jhotdraw.app.action.ExportAction"},
 {"id":14, "superclassid":"19", "superclassname":"org.jhotdraw.app.action.AbstractViewAction", "ownerclassid":"32", "ownerclassname":"org.jhotdraw.app.action.FindAction"},
 {"id":15, "superclassid":"18", "superclassname":"org.jhotdraw.app.action.AbstractSaveBeforeAction", "ownerclassid":"34", "ownerclassname":"org.jhotdraw.app.action.LoadAction"},
 {"id":16, "superclassid":"34", "superclassname":"org.jhotdraw.app.action.LoadAction", "ownerclassid":"35", "ownerclassname":"org.jhotdraw.app.action.LoadDirectoryAction"},
 {"id":17, "superclassid":"18", "superclassname":"org.jhotdraw.app.action.AbstractSaveBeforeAction", "ownerclassid":"36", "ownerclassname":"org.jhotdraw.app.action.LoadRecentAction"},
 {"id":18, "superclassid":"19", "superclassname":"org.jhotdraw.app.action.AbstractViewAction", "ownerclassid":"37", "ownerclassname":"org.jhotdraw.app.action.MaximizeAction"},
 {"id":19, "superclassid":"19", "superclassname":"org.jhotdraw.app.action.AbstractViewAction", "ownerclassid":"38", "ownerclassname":"org.jhotdraw.app.action.MinimizeAction"},
 {"id":20, "superclassid":"17", "superclassname":"org.jhotdraw.app.action.AbstractApplicationAction", "ownerclassid":"39", "ownerclassname":"org.jhotdraw.app.action.NewAction"},
 {"id":21, "superclassid":"17", "superclassname":"org.jhotdraw.app.action.AbstractApplicationAction", "ownerclassid":"40", "ownerclassname":"org.jhotdraw.app.action.OSXDropOnDockAction"},
 {"id":22, "superclassid":"17", "superclassname":"org.jhotdraw.app.action.AbstractApplicationAction", "ownerclassid":"42", "ownerclassname":"org.jhotdraw.app.action.OpenAction"},
 {"id":23, "superclassid":"42", "superclassname":"org.jhotdraw.app.action.OpenAction", "ownerclassid":"43", "ownerclassname":"org.jhotdraw.app.action.OpenDirectoryAction"},
 {"id":24, "superclassid":"17", "superclassname":"org.jhotdraw.app.action.AbstractApplicationAction", "ownerclassid":"44", "ownerclassname":"org.jhotdraw.app.action.OpenRecentAction"},
 {"id":25, "superclassid":"19", "superclassname":"org.jhotdraw.app.action.AbstractViewAction", "ownerclassid":"46", "ownerclassname":"org.jhotdraw.app.action.PrintAction"},
 {"id":26, "superclassid":"19", "superclassname":"org.jhotdraw.app.action.AbstractViewAction", "ownerclassid":"47", "ownerclassname":"org.jhotdraw.app.action.RedoAction"},
 {"id":27, "superclassid":"19", "superclassname":"org.jhotdraw.app.action.AbstractViewAction", "ownerclassid":"48", "ownerclassname":"org.jhotdraw.app.action.SaveAction"},
 {"id":28, "superclassid":"48", "superclassname":"org.jhotdraw.app.action.SaveAction", "ownerclassid":"49", "ownerclassname":"org.jhotdraw.app.action.SaveAsAction"},
 {"id":29, "superclassid":"19", "superclassname":"org.jhotdraw.app.action.AbstractViewAction", "ownerclassid":"52", "ownerclassname":"org.jhotdraw.app.action.ToggleViewPropertyAction"},
 {"id":30, "superclassid":"19", "superclassname":"org.jhotdraw.app.action.AbstractViewAction", "ownerclassid":"54", "ownerclassname":"org.jhotdraw.app.action.UndoAction"},
 {"id":31, "superclassid":"19", "superclassname":"org.jhotdraw.app.action.AbstractViewAction", "ownerclassid":"55", "ownerclassname":"org.jhotdraw.app.action.ViewPropertyAction"},
 {"id":32, "superclassid":"56", "superclassname":"org.jhotdraw.beans.AbstractBean", "ownerclassid":"57", "ownerclassname":"org.jhotdraw.color.AbstractColorSlidersModel"},
 {"id":33, "superclassid":"58", "superclassname":"org.jhotdraw.color.AbstractColorSystem", "ownerclassid":"60", "ownerclassname":"org.jhotdraw.color.CMYKICCColorSystem"},
 {"id":34, "superclassid":"58", "superclassname":"org.jhotdraw.color.AbstractColorSystem", "ownerclassid":"61", "ownerclassname":"org.jhotdraw.color.CMYKNominalColorSystem"},
 {"id":35, "superclassid":"57", "superclassname":"org.jhotdraw.color.AbstractColorSlidersModel", "ownerclassid":"73", "ownerclassname":"org.jhotdraw.color.DefaultColorSliderModel"},
 {"id":36, "superclassid":"71", "superclassname":"org.jhotdraw.color.ColorWheelImageProducer", "ownerclassid":"75", "ownerclassname":"org.jhotdraw.color.HSLHarmonicColorWheelImageProducer"},
 {"id":37, "superclassid":"58", "superclassname":"org.jhotdraw.color.AbstractColorSystem", "ownerclassid":"76", "ownerclassname":"org.jhotdraw.color.HSLRGBColorSystem"},
 {"id":38, "superclassid":"58", "superclassname":"org.jhotdraw.color.AbstractColorSystem", "ownerclassid":"77", "ownerclassname":"org.jhotdraw.color.HSLRYBColorSystem"},
 {"id":39, "superclassid":"71", "superclassname":"org.jhotdraw.color.ColorWheelImageProducer", "ownerclassid":"78", "ownerclassname":"org.jhotdraw.color.HSVHarmonicColorWheelImageProducer"},
 {"id":40, "superclassid":"58", "superclassname":"org.jhotdraw.color.AbstractColorSystem", "ownerclassid":"79", "ownerclassname":"org.jhotdraw.color.HSVRGBColorSystem"},
 {"id":41, "superclassid":"58", "superclassname":"org.jhotdraw.color.AbstractColorSystem", "ownerclassid":"80", "ownerclassname":"org.jhotdraw.color.HSVRYBColorSystem"},
 {"id":42, "superclassid":"85", "superclassname":"org.jhotdraw.color.JColorWheel", "ownerclassid":"88", "ownerclassname":"org.jhotdraw.color.JHarmonicColorWheel"},
 {"id":43, "superclassid":"58", "superclassname":"org.jhotdraw.color.AbstractColorSystem", "ownerclassid":"89", "ownerclassname":"org.jhotdraw.color.RGBColorSystem"},
 {"id":44, "superclassid":"59", "superclassname":"org.jhotdraw.color.AbstractHarmonicRule", "ownerclassid":"90", "ownerclassname":"org.jhotdraw.color.SimpleHarmonicRule"},
 {"id":45, "superclassid":"95", "superclassname":"org.jhotdraw.draw.AbstractCompositeFigure", "ownerclassid":"91", "ownerclassname":"org.jhotdraw.draw.AbstractAttributedCompositeFigure"},
 {"id":46, "superclassid":"93", "superclassname":"org.jhotdraw.draw.AbstractAttributedFigure", "ownerclassid":"92", "ownerclassname":"org.jhotdraw.draw.AbstractAttributedDecoratedFigure"},
 {"id":47, "superclassid":"100", "superclassname":"org.jhotdraw.draw.AbstractFigure", "ownerclassid":"93", "ownerclassname":"org.jhotdraw.draw.AbstractAttributedFigure"},
 {"id":48, "superclassid":"100", "superclassname":"org.jhotdraw.draw.AbstractFigure", "ownerclassid":"95", "ownerclassname":"org.jhotdraw.draw.AbstractCompositeFigure"},
 {"id":49, "superclassid":"175", "superclassname":"org.jhotdraw.draw.FigureAdapter", "ownerclassid":"94", "ownerclassname":"org.jhotdraw.draw.AbstractCompositeFigure$EventHandler"},
 {"id":50, "superclassid":"101", "superclassname":"org.jhotdraw.draw.AbstractHandle", "ownerclassid":"96", "ownerclassname":"org.jhotdraw.draw.AbstractConnectionHandle"},
 {"id":51, "superclassid":"56", "superclassname":"org.jhotdraw.beans.AbstractBean", "ownerclassid":"98", "ownerclassname":"org.jhotdraw.draw.AbstractConstrainer"},
 {"id":52, "superclassid":"91", "superclassname":"org.jhotdraw.draw.AbstractAttributedCompositeFigure", "ownerclassid":"99", "ownerclassname":"org.jhotdraw.draw.AbstractDrawing"},
 {"id":53, "superclassid":"56", "superclassname":"org.jhotdraw.beans.AbstractBean", "ownerclassid":"100", "ownerclassname":"org.jhotdraw.draw.AbstractFigure"},
 {"id":54, "superclassid":"101", "superclassname":"org.jhotdraw.draw.AbstractHandle", "ownerclassid":"105", "ownerclassname":"org.jhotdraw.draw.AbstractRotateHandle"},
 {"id":55, "superclassid":"56", "superclassname":"org.jhotdraw.beans.AbstractBean", "ownerclassid":"106", "ownerclassname":"org.jhotdraw.draw.AbstractTool"},
 {"id":56, "superclassid":"103", "superclassname":"org.jhotdraw.draw.AbstractLineDecoration", "ownerclassid":"107", "ownerclassname":"org.jhotdraw.draw.ArrowTip"},
 {"id":57, "superclassid":"101", "superclassname":"org.jhotdraw.draw.AbstractHandle", "ownerclassid":"117", "ownerclassname":"org.jhotdraw.draw.BezierControlPointHandle"},
 {"id":58, "superclassid":"93", "superclassname":"org.jhotdraw.draw.AbstractAttributedFigure", "ownerclassid":"118", "ownerclassname":"org.jhotdraw.draw.BezierFigure"},
 {"id":59, "superclassid":"101", "superclassname":"org.jhotdraw.draw.AbstractHandle", "ownerclassid":"121", "ownerclassname":"org.jhotdraw.draw.BezierNodeHandle"},
 {"id":60, "superclassid":"101", "superclassname":"org.jhotdraw.draw.AbstractHandle", "ownerclassid":"122", "ownerclassname":"org.jhotdraw.draw.BezierOutlineHandle"},
 {"id":61, "superclassid":"104", "superclassname":"org.jhotdraw.draw.AbstractLocator", "ownerclassid":"123", "ownerclassname":"org.jhotdraw.draw.BezierPointLocator"},
 {"id":62, "superclassid":"101", "superclassname":"org.jhotdraw.draw.AbstractHandle", "ownerclassid":"124", "ownerclassname":"org.jhotdraw.draw.BezierScaleHandle"},
 {"id":63, "superclassid":"106", "superclassname":"org.jhotdraw.draw.AbstractTool", "ownerclassid":"125", "ownerclassname":"org.jhotdraw.draw.BezierTool"},
 {"id":64, "superclassid":"106", "superclassname":"org.jhotdraw.draw.AbstractTool", "ownerclassid":"126", "ownerclassname":"org.jhotdraw.draw.BidirectionalConnectionTool"},
 {"id":65, "superclassid":"228", "superclassname":"org.jhotdraw.draw.RectangleFigure", "ownerclassid":"127", "ownerclassname":"org.jhotdraw.draw.BorderRectangleFigure"},
 {"id":66, "superclassid":"101", "superclassname":"org.jhotdraw.draw.AbstractHandle", "ownerclassid":"128", "ownerclassname":"org.jhotdraw.draw.BoundsOutlineHandle"},
 {"id":67, "superclassid":"132", "superclassname":"org.jhotdraw.draw.ChopRectangleConnector", "ownerclassid":"129", "ownerclassname":"org.jhotdraw.draw.ChopBezierConnector"},
 {"id":68, "superclassid":"132", "superclassname":"org.jhotdraw.draw.ChopRectangleConnector", "ownerclassid":"130", "ownerclassname":"org.jhotdraw.draw.ChopDiamondConnector"},
 {"id":69, "superclassid":"132", "superclassname":"org.jhotdraw.draw.ChopRectangleConnector", "ownerclassid":"131", "ownerclassname":"org.jhotdraw.draw.ChopEllipseConnector"},
 {"id":70, "superclassid":"97", "superclassname":"org.jhotdraw.draw.AbstractConnector", "ownerclassid":"132", "ownerclassname":"org.jhotdraw.draw.ChopRectangleConnector"},
 {"id":71, "superclassid":"132", "superclassname":"org.jhotdraw.draw.ChopRectangleConnector", "ownerclassid":"133", "ownerclassname":"org.jhotdraw.draw.ChopRoundRectangleConnector"},
 {"id":72, "superclassid":"132", "superclassname":"org.jhotdraw.draw.ChopRectangleConnector", "ownerclassid":"134", "ownerclassname":"org.jhotdraw.draw.ChopTriangleConnector"},
 {"id":73, "superclassid":"216", "superclassname":"org.jhotdraw.draw.LocatorHandle", "ownerclassid":"135", "ownerclassname":"org.jhotdraw.draw.CloseHandle"},
 {"id":74, "superclassid":"96", "superclassname":"org.jhotdraw.draw.AbstractConnectionHandle", "ownerclassid":"141", "ownerclassname":"org.jhotdraw.draw.ConnectionEndHandle"},
 {"id":75, "superclassid":"96", "superclassname":"org.jhotdraw.draw.AbstractConnectionHandle", "ownerclassid":"143", "ownerclassname":"org.jhotdraw.draw.ConnectionStartHandle"},
 {"id":76, "superclassid":"106", "superclassname":"org.jhotdraw.draw.AbstractTool", "ownerclassid":"144", "ownerclassname":"org.jhotdraw.draw.ConnectionTool"},
 {"id":77, "superclassid":"101", "superclassname":"org.jhotdraw.draw.AbstractHandle", "ownerclassid":"146", "ownerclassname":"org.jhotdraw.draw.ConnectorHandle"},
 {"id":78, "superclassid":"106", "superclassname":"org.jhotdraw.draw.AbstractTool", "ownerclassid":"148", "ownerclassname":"org.jhotdraw.draw.CreationTool"},
 {"id":79, "superclassid":"106", "superclassname":"org.jhotdraw.draw.AbstractTool", "ownerclassid":"151", "ownerclassname":"org.jhotdraw.draw.DefaultDragTracker"},
 {"id":80, "superclassid":"99", "superclassname":"org.jhotdraw.draw.AbstractDrawing", "ownerclassid":"152", "ownerclassname":"org.jhotdraw.draw.DefaultDrawing"},
 {"id":81, "superclassid":"56", "superclassname":"org.jhotdraw.beans.AbstractBean", "ownerclassid":"153", "ownerclassname":"org.jhotdraw.draw.DefaultDrawingEditor"},
 {"id":82, "superclassid":"106", "superclassname":"org.jhotdraw.draw.AbstractTool", "ownerclassid":"160", "ownerclassname":"org.jhotdraw.draw.DefaultHandleTracker"},
 {"id":83, "superclassid":"106", "superclassname":"org.jhotdraw.draw.AbstractTool", "ownerclassid":"161", "ownerclassname":"org.jhotdraw.draw.DefaultSelectAreaTracker"},
 {"id":84, "superclassid":"248", "superclassname":"org.jhotdraw.draw.SelectionTool", "ownerclassid":"162", "ownerclassname":"org.jhotdraw.draw.DelegationSelectionTool"},
 {"id":85, "superclassid":"93", "superclassname":"org.jhotdraw.draw.AbstractAttributedFigure", "ownerclassid":"163", "ownerclassname":"org.jhotdraw.draw.DiamondFigure"},
 {"id":86, "superclassid":"159", "superclassname":"org.jhotdraw.draw.DefaultDrawingViewTransferHandler", "ownerclassid":"164", "ownerclassname":"org.jhotdraw.draw.DnDDrawingViewTransferHandler"},
 {"id":87, "superclassid":"106", "superclassname":"org.jhotdraw.draw.AbstractTool", "ownerclassid":"165", "ownerclassname":"org.jhotdraw.draw.DnDTracker"},
 {"id":88, "superclassid":"101", "superclassname":"org.jhotdraw.draw.AbstractHandle", "ownerclassid":"166", "ownerclassname":"org.jhotdraw.draw.DragHandle"},
 {"id":89, "superclassid":"93", "superclassname":"org.jhotdraw.draw.AbstractAttributedFigure", "ownerclassid":"173", "ownerclassname":"org.jhotdraw.draw.EllipseFigure"},
 {"id":90, "superclassid":"216", "superclassname":"org.jhotdraw.draw.LocatorHandle", "ownerclassid":"183", "ownerclassname":"org.jhotdraw.draw.FontSizeHandle"},
 {"id":91, "superclassid":"103", "superclassname":"org.jhotdraw.draw.AbstractLineDecoration", "ownerclassid":"185", "ownerclassname":"org.jhotdraw.draw.GeneralPathTip"},
 {"id":92, "superclassid":"95", "superclassname":"org.jhotdraw.draw.AbstractCompositeFigure", "ownerclassid":"188", "ownerclassname":"org.jhotdraw.draw.GraphicalCompositeFigure"},
 {"id":93, "superclassid":"175", "superclassname":"org.jhotdraw.draw.FigureAdapter", "ownerclassid":"187", "ownerclassname":"org.jhotdraw.draw.GraphicalCompositeFigure$PresentationFigureHandler"},
 {"id":94, "superclassid":"98", "superclassname":"org.jhotdraw.draw.AbstractConstrainer", "ownerclassid":"189", "ownerclassname":"org.jhotdraw.draw.GridConstrainer"},
 {"id":95, "superclassid":"95", "superclassname":"org.jhotdraw.draw.AbstractCompositeFigure", "ownerclassid":"190", "ownerclassname":"org.jhotdraw.draw.GroupFigure"},
 {"id":96, "superclassid":"102", "superclassname":"org.jhotdraw.draw.AbstractLayouter", "ownerclassid":"197", "ownerclassname":"org.jhotdraw.draw.HorizontalLayouter"},
 {"id":97, "superclassid":"92", "superclassname":"org.jhotdraw.draw.AbstractAttributedDecoratedFigure", "ownerclassid":"198", "ownerclassname":"org.jhotdraw.draw.ImageFigure"},
 {"id":98, "superclassid":"148", "superclassname":"org.jhotdraw.draw.CreationTool", "ownerclassid":"202", "ownerclassname":"org.jhotdraw.draw.ImageTool"},
 {"id":99, "superclassid":"258", "superclassname":"org.jhotdraw.draw.TextFigure", "ownerclassid":"204", "ownerclassname":"org.jhotdraw.draw.LabelFigure"},
 {"id":100, "superclassid":"209", "superclassname":"org.jhotdraw.draw.LineConnectionFigure", "ownerclassid":"206", "ownerclassname":"org.jhotdraw.draw.LabeledLineConnectionFigure"},
 {"id":101, "superclassid":"175", "superclassname":"org.jhotdraw.draw.FigureAdapter", "ownerclassid":"205", "ownerclassname":"org.jhotdraw.draw.LabeledLineConnectionFigure$ChildHandler"},
 {"id":102, "superclassid":"211", "superclassname":"org.jhotdraw.draw.LineFigure", "ownerclassid":"209", "ownerclassname":"org.jhotdraw.draw.LineConnectionFigure"},
 {"id":103, "superclassid":"175", "superclassname":"org.jhotdraw.draw.FigureAdapter", "ownerclassid":"208", "ownerclassname":"org.jhotdraw.draw.LineConnectionFigure$ConnectionHandler"},
 {"id":104, "superclassid":"118", "superclassname":"org.jhotdraw.draw.BezierFigure", "ownerclassid":"211", "ownerclassname":"org.jhotdraw.draw.LineFigure"},
 {"id":105, "superclassid":"188", "superclassname":"org.jhotdraw.draw.GraphicalCompositeFigure", "ownerclassid":"213", "ownerclassname":"org.jhotdraw.draw.ListFigure"},
 {"id":106, "superclassid":"97", "superclassname":"org.jhotdraw.draw.AbstractConnector", "ownerclassid":"215", "ownerclassname":"org.jhotdraw.draw.LocatorConnector"},
 {"id":107, "superclassid":"101", "superclassname":"org.jhotdraw.draw.AbstractHandle", "ownerclassid":"216", "ownerclassname":"org.jhotdraw.draw.LocatorHandle"},
 {"id":108, "superclassid":"216", "superclassname":"org.jhotdraw.draw.LocatorHandle", "ownerclassid":"218", "ownerclassname":"org.jhotdraw.draw.MoveHandle"},
 {"id":109, "superclassid":"216", "superclassname":"org.jhotdraw.draw.LocatorHandle", "ownerclassid":"219", "ownerclassname":"org.jhotdraw.draw.NullHandle"},
 {"id":110, "superclassid":"103", "superclassname":"org.jhotdraw.draw.AbstractLineDecoration", "ownerclassid":"222", "ownerclassname":"org.jhotdraw.draw.PerpendicularBar"},
 {"id":111, "superclassid":"95", "superclassname":"org.jhotdraw.draw.AbstractCompositeFigure", "ownerclassid":"225", "ownerclassname":"org.jhotdraw.draw.QuadTreeCompositeFigure"},
 {"id":112, "superclassid":"175", "superclassname":"org.jhotdraw.draw.FigureAdapter", "ownerclassid":"224", "ownerclassname":"org.jhotdraw.draw.QuadTreeCompositeFigure$FigureHandler"},
 {"id":113, "superclassid":"99", "superclassname":"org.jhotdraw.draw.AbstractDrawing", "ownerclassid":"227", "ownerclassname":"org.jhotdraw.draw.QuadTreeDrawing"},
 {"id":114, "superclassid":"93", "superclassname":"org.jhotdraw.draw.AbstractAttributedFigure", "ownerclassid":"228", "ownerclassname":"org.jhotdraw.draw.RectangleFigure"},
 {"id":115, "superclassid":"230", "superclassname":"org.jhotdraw.draw.RelativeLocator", "ownerclassid":"229", "ownerclassname":"org.jhotdraw.draw.RelativeDecoratorLocator"},
 {"id":116, "superclassid":"104", "superclassname":"org.jhotdraw.draw.AbstractLocator", "ownerclassid":"230", "ownerclassname":"org.jhotdraw.draw.RelativeLocator"},
 {"id":117, "superclassid":"216", "superclassname":"org.jhotdraw.draw.LocatorHandle", "ownerclassid":"235", "ownerclassname":"org.jhotdraw.draw.ResizeHandleKit$ResizeHandle"},
 {"id":118, "superclassid":"105", "superclassname":"org.jhotdraw.draw.AbstractRotateHandle", "ownerclassid":"242", "ownerclassname":"org.jhotdraw.draw.RotateHandle"},
 {"id":119, "superclassid":"93", "superclassname":"org.jhotdraw.draw.AbstractAttributedFigure", "ownerclassid":"244", "ownerclassname":"org.jhotdraw.draw.RoundRectangleFigure"},
 {"id":120, "superclassid":"101", "superclassname":"org.jhotdraw.draw.AbstractHandle", "ownerclassid":"245", "ownerclassname":"org.jhotdraw.draw.RoundRectangleRadiusHandle"},
 {"id":121, "superclassid":"106", "superclassname":"org.jhotdraw.draw.AbstractTool", "ownerclassid":"248", "ownerclassname":"org.jhotdraw.draw.SelectionTool"},
 {"id":122, "superclassid":"132", "superclassname":"org.jhotdraw.draw.ChopRectangleConnector", "ownerclassid":"252", "ownerclassname":"org.jhotdraw.draw.StickyRectangleConnector"},
 {"id":123, "superclassid":"148", "superclassname":"org.jhotdraw.draw.CreationTool", "ownerclassid":"253", "ownerclassname":"org.jhotdraw.draw.TextAreaCreationTool"},
 {"id":124, "superclassid":"106", "superclassname":"org.jhotdraw.draw.AbstractTool", "ownerclassid":"254", "ownerclassname":"org.jhotdraw.draw.TextAreaEditingTool"},
 {"id":125, "superclassid":"92", "superclassname":"org.jhotdraw.draw.AbstractAttributedDecoratedFigure", "ownerclassid":"255", "ownerclassname":"org.jhotdraw.draw.TextAreaFigure"},
 {"id":126, "superclassid":"148", "superclassname":"org.jhotdraw.draw.CreationTool", "ownerclassid":"256", "ownerclassname":"org.jhotdraw.draw.TextCreationTool"},
 {"id":127, "superclassid":"106", "superclassname":"org.jhotdraw.draw.AbstractTool", "ownerclassid":"257", "ownerclassname":"org.jhotdraw.draw.TextEditingTool"},
 {"id":128, "superclassid":"92", "superclassname":"org.jhotdraw.draw.AbstractAttributedDecoratedFigure", "ownerclassid":"258", "ownerclassname":"org.jhotdraw.draw.TextFigure"},
 {"id":129, "superclassid":"101", "superclassname":"org.jhotdraw.draw.AbstractHandle", "ownerclassid":"261", "ownerclassname":"org.jhotdraw.draw.TextOverflowHandle"},
 {"id":130, "superclassid":"216", "superclassname":"org.jhotdraw.draw.LocatorHandle", "ownerclassid":"273", "ownerclassname":"org.jhotdraw.draw.TransformHandleKit$TransformHandle"},
 {"id":131, "superclassid":"93", "superclassname":"org.jhotdraw.draw.AbstractAttributedFigure", "ownerclassid":"277", "ownerclassname":"org.jhotdraw.draw.TriangleFigure"},
 {"id":132, "superclassid":"101", "superclassname":"org.jhotdraw.draw.AbstractHandle", "ownerclassid":"278", "ownerclassname":"org.jhotdraw.draw.TriangleRotationHandler"},
 {"id":133, "superclassid":"102", "superclassname":"org.jhotdraw.draw.AbstractLayouter", "ownerclassid":"279", "ownerclassname":"org.jhotdraw.draw.VerticalLayouter"},
 {"id":134, "superclassid":"283", "superclassname":"org.jhotdraw.draw.action.AbstractSelectedAction", "ownerclassid":"290", "ownerclassname":"org.jhotdraw.draw.action.AlignAction"},
 {"id":135, "superclassid":"290", "superclassname":"org.jhotdraw.draw.action.AlignAction", "ownerclassid":"284", "ownerclassname":"org.jhotdraw.draw.action.AlignAction$East"},
 {"id":136, "superclassid":"290", "superclassname":"org.jhotdraw.draw.action.AlignAction", "ownerclassid":"285", "ownerclassname":"org.jhotdraw.draw.action.AlignAction$Horizontal"},
 {"id":137, "superclassid":"290", "superclassname":"org.jhotdraw.draw.action.AlignAction", "ownerclassid":"286", "ownerclassname":"org.jhotdraw.draw.action.AlignAction$North"},
 {"id":138, "superclassid":"290", "superclassname":"org.jhotdraw.draw.action.AlignAction", "ownerclassid":"287", "ownerclassname":"org.jhotdraw.draw.action.AlignAction$South"},
 {"id":139, "superclassid":"290", "superclassname":"org.jhotdraw.draw.action.AlignAction", "ownerclassid":"288", "ownerclassname":"org.jhotdraw.draw.action.AlignAction$Vertical"},
 {"id":140, "superclassid":"290", "superclassname":"org.jhotdraw.draw.action.AlignAction", "ownerclassid":"289", "ownerclassname":"org.jhotdraw.draw.action.AlignAction$West"},
 {"id":141, "superclassid":"283", "superclassname":"org.jhotdraw.draw.action.AbstractSelectedAction", "ownerclassid":"291", "ownerclassname":"org.jhotdraw.draw.action.ApplyAttributesAction"},
 {"id":142, "superclassid":"283", "superclassname":"org.jhotdraw.draw.action.AbstractSelectedAction", "ownerclassid":"292", "ownerclassname":"org.jhotdraw.draw.action.AttributeAction"},
 {"id":143, "superclassid":"283", "superclassname":"org.jhotdraw.draw.action.AbstractSelectedAction", "ownerclassid":"294", "ownerclassname":"org.jhotdraw.draw.action.BringToFrontAction"},
 {"id":144, "superclassid":"283", "superclassname":"org.jhotdraw.draw.action.AbstractSelectedAction", "ownerclassid":"299", "ownerclassname":"org.jhotdraw.draw.action.DefaultAttributeAction"},
 {"id":145, "superclassid":"281", "superclassname":"org.jhotdraw.draw.action.AbstractDrawingViewAction", "ownerclassid":"300", "ownerclassname":"org.jhotdraw.draw.action.DrawingAttributeAction"},
 {"id":146, "superclassid":"309", "superclassname":"org.jhotdraw.draw.action.EditorColorChooserAction", "ownerclassid":"301", "ownerclassname":"org.jhotdraw.draw.action.DrawingColorChooserAction"},
 {"id":147, "superclassid":"56", "superclassname":"org.jhotdraw.beans.AbstractBean", "ownerclassid":"304", "ownerclassname":"org.jhotdraw.draw.action.DrawingEditorProxy"},
 {"id":148, "superclassid":"280", "superclassname":"org.jhotdraw.draw.action.AbstractDrawingEditorAction", "ownerclassid":"305", "ownerclassname":"org.jhotdraw.draw.action.EditCanvasAction"},
 {"id":149, "superclassid":"280", "superclassname":"org.jhotdraw.draw.action.AbstractDrawingEditorAction", "ownerclassid":"307", "ownerclassname":"org.jhotdraw.draw.action.EditGridAction"},
 {"id":150, "superclassid":"292", "superclassname":"org.jhotdraw.draw.action.AttributeAction", "ownerclassid":"309", "ownerclassname":"org.jhotdraw.draw.action.EditorColorChooserAction"},
 {"id":151, "superclassid":"283", "superclassname":"org.jhotdraw.draw.action.AbstractSelectedAction", "ownerclassid":"311", "ownerclassname":"org.jhotdraw.draw.action.FontChooserHandler"},
 {"id":152, "superclassid":"283", "superclassname":"org.jhotdraw.draw.action.AbstractSelectedAction", "ownerclassid":"314", "ownerclassname":"org.jhotdraw.draw.action.GroupAction"},
 {"id":153, "superclassid":"283", "superclassname":"org.jhotdraw.draw.action.AbstractSelectedAction", "ownerclassid":"316", "ownerclassname":"org.jhotdraw.draw.action.IncreaseHandleDetailLevelAction"},
 {"id":154, "superclassid":"283", "superclassname":"org.jhotdraw.draw.action.AbstractSelectedAction", "ownerclassid":"322", "ownerclassname":"org.jhotdraw.draw.action.MoveAction"},
 {"id":155, "superclassid":"322", "superclassname":"org.jhotdraw.draw.action.MoveAction", "ownerclassid":"318", "ownerclassname":"org.jhotdraw.draw.action.MoveAction$East"},
 {"id":156, "superclassid":"322", "superclassname":"org.jhotdraw.draw.action.MoveAction", "ownerclassid":"319", "ownerclassname":"org.jhotdraw.draw.action.MoveAction$North"},
 {"id":157, "superclassid":"322", "superclassname":"org.jhotdraw.draw.action.MoveAction", "ownerclassid":"320", "ownerclassname":"org.jhotdraw.draw.action.MoveAction$South"},
 {"id":158, "superclassid":"322", "superclassname":"org.jhotdraw.draw.action.MoveAction", "ownerclassid":"321", "ownerclassname":"org.jhotdraw.draw.action.MoveAction$West"},
 {"id":159, "superclassid":"283", "superclassname":"org.jhotdraw.draw.action.AbstractSelectedAction", "ownerclassid":"327", "ownerclassname":"org.jhotdraw.draw.action.MoveConstrainedAction"},
 {"id":160, "superclassid":"327", "superclassname":"org.jhotdraw.draw.action.MoveConstrainedAction", "ownerclassid":"323", "ownerclassname":"org.jhotdraw.draw.action.MoveConstrainedAction$East"},
 {"id":161, "superclassid":"327", "superclassname":"org.jhotdraw.draw.action.MoveConstrainedAction", "ownerclassid":"324", "ownerclassname":"org.jhotdraw.draw.action.MoveConstrainedAction$North"},
 {"id":162, "superclassid":"327", "superclassname":"org.jhotdraw.draw.action.MoveConstrainedAction", "ownerclassid":"325", "ownerclassname":"org.jhotdraw.draw.action.MoveConstrainedAction$South"},
 {"id":163, "superclassid":"327", "superclassname":"org.jhotdraw.draw.action.MoveConstrainedAction", "ownerclassid":"326", "ownerclassname":"org.jhotdraw.draw.action.MoveConstrainedAction$West"},
 {"id":164, "superclassid":"283", "superclassname":"org.jhotdraw.draw.action.AbstractSelectedAction", "ownerclassid":"329", "ownerclassname":"org.jhotdraw.draw.action.PickAttributesAction"},
 {"id":165, "superclassid":"283", "superclassname":"org.jhotdraw.draw.action.AbstractSelectedAction", "ownerclassid":"330", "ownerclassname":"org.jhotdraw.draw.action.SelectSameAction"},
 {"id":166, "superclassid":"309", "superclassname":"org.jhotdraw.draw.action.EditorColorChooserAction", "ownerclassid":"331", "ownerclassname":"org.jhotdraw.draw.action.SelectionColorChooserAction"},
 {"id":167, "superclassid":"175", "superclassname":"org.jhotdraw.draw.FigureAdapter", "ownerclassid":"333", "ownerclassname":"org.jhotdraw.draw.action.SelectionComponentRepainter"},
 {"id":168, "superclassid":"283", "superclassname":"org.jhotdraw.draw.action.AbstractSelectedAction", "ownerclassid":"334", "ownerclassname":"org.jhotdraw.draw.action.SendToBackAction"},
 {"id":169, "superclassid":"280", "superclassname":"org.jhotdraw.draw.action.AbstractDrawingEditorAction", "ownerclassid":"336", "ownerclassname":"org.jhotdraw.draw.action.ToggleGridAction"},
 {"id":170, "superclassid":"314", "superclassname":"org.jhotdraw.draw.action.GroupAction", "ownerclassid":"337", "ownerclassname":"org.jhotdraw.draw.action.UngroupAction"},
 {"id":171, "superclassid":"281", "superclassname":"org.jhotdraw.draw.action.AbstractDrawingViewAction", "ownerclassid":"339", "ownerclassname":"org.jhotdraw.draw.action.ZoomAction"},
 {"id":172, "superclassid":"280", "superclassname":"org.jhotdraw.draw.action.AbstractDrawingEditorAction", "ownerclassid":"340", "ownerclassname":"org.jhotdraw.draw.action.ZoomEditorAction"},
 {"id":173, "superclassid":"347", "superclassname":"org.jhotdraw.geom.DoubleStroke", "ownerclassid":"349", "ownerclassname":"org.jhotdraw.geom.GrowStroke"},
 {"id":174, "superclassid":"352", "superclassname":"org.jhotdraw.geom.Insets2D", "ownerclassid":"350", "ownerclassname":"org.jhotdraw.geom.Insets2D$Double"},
 {"id":175, "superclassid":"352", "superclassname":"org.jhotdraw.geom.Insets2D", "ownerclassid":"351", "ownerclassname":"org.jhotdraw.geom.Insets2D$Float"},
 {"id":176, "superclassid":"357", "superclassname":"org.jhotdraw.geom.Polygon2D", "ownerclassid":"353", "ownerclassname":"org.jhotdraw.geom.Polygon2D$Double"},
 {"id":177, "superclassid":"357", "superclassname":"org.jhotdraw.geom.Polygon2D", "ownerclassid":"354", "ownerclassname":"org.jhotdraw.geom.Polygon2D$Float"},
 {"id":178, "superclassid":"175", "superclassname":"org.jhotdraw.draw.FigureAdapter", "ownerclassid":"361", "ownerclassname":"org.jhotdraw.gui.AbstractAttributeEditorHandler$EventHandler"},
 {"id":179, "superclassid":"381", "superclassname":"org.jhotdraw.gui.JLifeFormattedTextArea", "ownerclassid":"373", "ownerclassname":"org.jhotdraw.gui.JAttributeTextArea"},
 {"id":180, "superclassid":"383", "superclassname":"org.jhotdraw.gui.JLifeFormattedTextField", "ownerclassid":"375", "ownerclassname":"org.jhotdraw.gui.JAttributeTextField"},
 {"id":181, "superclassid":"392", "superclassname":"org.jhotdraw.gui.PlacardScrollPaneLayout", "ownerclassid":"391", "ownerclassname":"org.jhotdraw.gui.PlacardScrollPaneLayout$UIResource"},
 {"id":182, "superclassid":"395", "superclassname":"org.jhotdraw.gui.datatransfer.AbstractTransferable", "ownerclassid":"398", "ownerclassname":"org.jhotdraw.gui.datatransfer.InputStreamTransferable"},
 {"id":183, "superclassid":"401", "superclassname":"org.jhotdraw.gui.fontchooser.AbstractFontChooserModel", "ownerclassid":"403", "ownerclassname":"org.jhotdraw.gui.fontchooser.DefaultFontChooserModel"},
 {"id":184, "superclassid":"403", "superclassname":"org.jhotdraw.gui.fontchooser.DefaultFontChooserModel", "ownerclassid":"402", "ownerclassname":"org.jhotdraw.gui.fontchooser.DefaultFontChooserModel$UIResource"},
 {"id":185, "superclassid":"410", "superclassname":"org.jhotdraw.gui.plaf.palette.BackdropBorder", "ownerclassid":"409", "ownerclassname":"org.jhotdraw.gui.plaf.palette.BackdropBorder$UIResource"},
 {"id":186, "superclassid":"408", "superclassname":"org.jhotdraw.gui.plaf.FontChooserUI", "ownerclassid":"420", "ownerclassname":"org.jhotdraw.gui.plaf.palette.PaletteFontChooserUI"},
 {"id":187, "superclassid":"431", "superclassname":"org.jhotdraw.gui.plaf.palette.PaletteToolBarBorder", "ownerclassid":"430", "ownerclassname":"org.jhotdraw.gui.plaf.palette.PaletteToolBarBorder$UIResource"},
 {"id":188, "superclassid":"412", "superclassname":"org.jhotdraw.gui.plaf.palette.MultiIcon", "ownerclassid":"442", "ownerclassname":"org.jhotdraw.gui.plaf.palette.SliderThumbIcon"},
 {"id":189, "superclassid":"6", "superclassname":"org.jhotdraw.app.DefaultApplicationModel", "ownerclassid":"454", "ownerclassname":"org.jhotdraw.samples.draw.DrawApplicationModel"},
 {"id":190, "superclassid":"653", "superclassname":"org.jhotdraw.xml.DefaultDOMFactory", "ownerclassid":"455", "ownerclassname":"org.jhotdraw.samples.draw.DrawFigureFactory"},
 {"id":191, "superclassid":"2", "superclassname":"org.jhotdraw.app.AbstractView", "ownerclassid":"458", "ownerclassname":"org.jhotdraw.samples.draw.DrawView"},
 {"id":192, "superclassid":"209", "superclassname":"org.jhotdraw.draw.LineConnectionFigure", "ownerclassid":"480", "ownerclassname":"org.jhotdraw.samples.mini.SmartConnectionFigureSample$SmartConnectionFigure"},
 {"id":193, "superclassid":"93", "superclassname":"org.jhotdraw.draw.AbstractAttributedFigure", "ownerclassid":"482", "ownerclassname":"org.jhotdraw.samples.mini.StraightLineFigure"},
 {"id":194, "superclassid":"6", "superclassname":"org.jhotdraw.app.DefaultApplicationModel", "ownerclassid":"486", "ownerclassname":"org.jhotdraw.samples.net.NetApplicationModel"},
 {"id":195, "superclassid":"653", "superclassname":"org.jhotdraw.xml.DefaultDOMFactory", "ownerclassid":"487", "ownerclassname":"org.jhotdraw.samples.net.NetFactory"},
 {"id":196, "superclassid":"2", "superclassname":"org.jhotdraw.app.AbstractView", "ownerclassid":"489", "ownerclassname":"org.jhotdraw.samples.net.NetView"},
 {"id":197, "superclassid":"258", "superclassname":"org.jhotdraw.draw.TextFigure", "ownerclassid":"490", "ownerclassname":"org.jhotdraw.samples.net.figures.NodeFigure"},
 {"id":198, "superclassid":"6", "superclassname":"org.jhotdraw.app.DefaultApplicationModel", "ownerclassid":"493", "ownerclassname":"org.jhotdraw.samples.odg.ODGApplicationModel"},
 {"id":199, "superclassid":"116", "superclassname":"org.jhotdraw.draw.AttributeKeys", "ownerclassid":"494", "ownerclassname":"org.jhotdraw.samples.odg.ODGAttributeKeys"},
 {"id":200, "superclassid":"227", "superclassname":"org.jhotdraw.draw.QuadTreeDrawing", "ownerclassid":"498", "ownerclassname":"org.jhotdraw.samples.odg.ODGDrawing"},
 {"id":201, "superclassid":"2", "superclassname":"org.jhotdraw.app.AbstractView", "ownerclassid":"503", "ownerclassname":"org.jhotdraw.samples.odg.ODGView"},
 {"id":202, "superclassid":"125", "superclassname":"org.jhotdraw.draw.BezierTool", "ownerclassid":"504", "ownerclassname":"org.jhotdraw.samples.odg.PathTool"},
 {"id":203, "superclassid":"314", "superclassname":"org.jhotdraw.draw.action.GroupAction", "ownerclassid":"505", "ownerclassname":"org.jhotdraw.samples.odg.action.CombineAction"},
 {"id":204, "superclassid":"337", "superclassname":"org.jhotdraw.draw.action.UngroupAction", "ownerclassid":"506", "ownerclassname":"org.jhotdraw.samples.odg.action.SplitAction"},
 {"id":205, "superclassid":"19", "superclassname":"org.jhotdraw.app.action.AbstractViewAction", "ownerclassid":"507", "ownerclassname":"org.jhotdraw.samples.odg.action.TogglePropertiesPanelAction"},
 {"id":206, "superclassid":"93", "superclassname":"org.jhotdraw.draw.AbstractAttributedFigure", "ownerclassid":"508", "ownerclassname":"org.jhotdraw.samples.odg.figures.ODGAttributedFigure"},
 {"id":207, "superclassid":"118", "superclassname":"org.jhotdraw.draw.BezierFigure", "ownerclassid":"509", "ownerclassname":"org.jhotdraw.samples.odg.figures.ODGBezierFigure"},
 {"id":208, "superclassid":"508", "superclassname":"org.jhotdraw.samples.odg.figures.ODGAttributedFigure", "ownerclassid":"510", "ownerclassname":"org.jhotdraw.samples.odg.figures.ODGEllipseFigure"},
 {"id":209, "superclassid":"190", "superclassname":"org.jhotdraw.draw.GroupFigure", "ownerclassid":"512", "ownerclassname":"org.jhotdraw.samples.odg.figures.ODGGroupFigure"},
 {"id":210, "superclassid":"91", "superclassname":"org.jhotdraw.draw.AbstractAttributedCompositeFigure", "ownerclassid":"513", "ownerclassname":"org.jhotdraw.samples.odg.figures.ODGPathFigure"},
 {"id":211, "superclassid":"101", "superclassname":"org.jhotdraw.draw.AbstractHandle", "ownerclassid":"514", "ownerclassname":"org.jhotdraw.samples.odg.figures.ODGPathOutlineHandle"},
 {"id":212, "superclassid":"508", "superclassname":"org.jhotdraw.samples.odg.figures.ODGAttributedFigure", "ownerclassid":"515", "ownerclassname":"org.jhotdraw.samples.odg.figures.ODGRectFigure"},
 {"id":213, "superclassid":"101", "superclassname":"org.jhotdraw.draw.AbstractHandle", "ownerclassid":"516", "ownerclassname":"org.jhotdraw.samples.odg.figures.ODGRectRadiusHandle"},
 {"id":214, "superclassid":"6", "superclassname":"org.jhotdraw.app.DefaultApplicationModel", "ownerclassid":"527", "ownerclassname":"org.jhotdraw.samples.pert.PertApplicationModel"},
 {"id":215, "superclassid":"653", "superclassname":"org.jhotdraw.xml.DefaultDOMFactory", "ownerclassid":"528", "ownerclassname":"org.jhotdraw.samples.pert.PertFactory"},
 {"id":216, "superclassid":"2", "superclassname":"org.jhotdraw.app.AbstractView", "ownerclassid":"530", "ownerclassname":"org.jhotdraw.samples.pert.PertView"},
 {"id":217, "superclassid":"209", "superclassname":"org.jhotdraw.draw.LineConnectionFigure", "ownerclassid":"531", "ownerclassname":"org.jhotdraw.samples.pert.figures.DependencyFigure"},
 {"id":218, "superclassid":"211", "superclassname":"org.jhotdraw.draw.LineFigure", "ownerclassid":"532", "ownerclassname":"org.jhotdraw.samples.pert.figures.SeparatorLineFigure"},
 {"id":219, "superclassid":"188", "superclassname":"org.jhotdraw.draw.GraphicalCompositeFigure", "ownerclassid":"535", "ownerclassname":"org.jhotdraw.samples.pert.figures.TaskFigure"},
 {"id":220, "superclassid":"175", "superclassname":"org.jhotdraw.draw.FigureAdapter", "ownerclassid":"533", "ownerclassname":"org.jhotdraw.samples.pert.figures.TaskFigure$DurationAdapter"},
 {"id":221, "superclassid":"175", "superclassname":"org.jhotdraw.draw.FigureAdapter", "ownerclassid":"534", "ownerclassname":"org.jhotdraw.samples.pert.figures.TaskFigure$NameAdapter"},
 {"id":222, "superclassid":"125", "superclassname":"org.jhotdraw.draw.BezierTool", "ownerclassid":"539", "ownerclassname":"org.jhotdraw.samples.svg.PathTool"},
 {"id":223, "superclassid":"6", "superclassname":"org.jhotdraw.app.DefaultApplicationModel", "ownerclassid":"542", "ownerclassname":"org.jhotdraw.samples.svg.SVGApplicationModel"},
 {"id":224, "superclassid":"116", "superclassname":"org.jhotdraw.draw.AttributeKeys", "ownerclassid":"545", "ownerclassname":"org.jhotdraw.samples.svg.SVGAttributeKeys"},
 {"id":225, "superclassid":"148", "superclassname":"org.jhotdraw.draw.CreationTool", "ownerclassid":"547", "ownerclassname":"org.jhotdraw.samples.svg.SVGCreateFromFileTool"},
 {"id":226, "superclassid":"2", "superclassname":"org.jhotdraw.app.AbstractView", "ownerclassid":"552", "ownerclassname":"org.jhotdraw.samples.svg.SVGView"},
 {"id":227, "superclassid":"283", "superclassname":"org.jhotdraw.draw.action.AbstractSelectedAction", "ownerclassid":"553", "ownerclassname":"org.jhotdraw.samples.svg.action.CombineAction"},
 {"id":228, "superclassid":"553", "superclassname":"org.jhotdraw.samples.svg.action.CombineAction", "ownerclassid":"554", "ownerclassname":"org.jhotdraw.samples.svg.action.SplitAction"},
 {"id":229, "superclassid":"19", "superclassname":"org.jhotdraw.app.action.AbstractViewAction", "ownerclassid":"555", "ownerclassname":"org.jhotdraw.samples.svg.action.ViewSourceAction"},
 {"id":230, "superclassid":"101", "superclassname":"org.jhotdraw.draw.AbstractHandle", "ownerclassid":"556", "ownerclassname":"org.jhotdraw.samples.svg.figures.ConvexHullOutlineHandle"},
 {"id":231, "superclassid":"101", "superclassname":"org.jhotdraw.draw.AbstractHandle", "ownerclassid":"557", "ownerclassname":"org.jhotdraw.samples.svg.figures.LinkHandle"},
 {"id":232, "superclassid":"93", "superclassname":"org.jhotdraw.draw.AbstractAttributedFigure", "ownerclassid":"558", "ownerclassname":"org.jhotdraw.samples.svg.figures.SVGAttributedFigure"},
 {"id":233, "superclassid":"118", "superclassname":"org.jhotdraw.draw.BezierFigure", "ownerclassid":"559", "ownerclassname":"org.jhotdraw.samples.svg.figures.SVGBezierFigure"},
 {"id":234, "superclassid":"558", "superclassname":"org.jhotdraw.samples.svg.figures.SVGAttributedFigure", "ownerclassid":"560", "ownerclassname":"org.jhotdraw.samples.svg.figures.SVGEllipseFigure"},
 {"id":235, "superclassid":"190", "superclassname":"org.jhotdraw.draw.GroupFigure", "ownerclassid":"562", "ownerclassname":"org.jhotdraw.samples.svg.figures.SVGGroupFigure"},
 {"id":236, "superclassid":"558", "superclassname":"org.jhotdraw.samples.svg.figures.SVGAttributedFigure", "ownerclassid":"563", "ownerclassname":"org.jhotdraw.samples.svg.figures.SVGImageFigure"},
 {"id":237, "superclassid":"91", "superclassname":"org.jhotdraw.draw.AbstractAttributedCompositeFigure", "ownerclassid":"564", "ownerclassname":"org.jhotdraw.samples.svg.figures.SVGPathFigure"},
 {"id":238, "superclassid":"101", "superclassname":"org.jhotdraw.draw.AbstractHandle", "ownerclassid":"565", "ownerclassname":"org.jhotdraw.samples.svg.figures.SVGPathOutlineHandle"},
 {"id":239, "superclassid":"558", "superclassname":"org.jhotdraw.samples.svg.figures.SVGAttributedFigure", "ownerclassid":"566", "ownerclassname":"org.jhotdraw.samples.svg.figures.SVGRectFigure"},
 {"id":240, "superclassid":"101", "superclassname":"org.jhotdraw.draw.AbstractHandle", "ownerclassid":"567", "ownerclassname":"org.jhotdraw.samples.svg.figures.SVGRectRadiusHandle"},
 {"id":241, "superclassid":"558", "superclassname":"org.jhotdraw.samples.svg.figures.SVGAttributedFigure", "ownerclassid":"569", "ownerclassname":"org.jhotdraw.samples.svg.figures.SVGTextAreaFigure"},
 {"id":242, "superclassid":"558", "superclassname":"org.jhotdraw.samples.svg.figures.SVGAttributedFigure", "ownerclassid":"570", "ownerclassname":"org.jhotdraw.samples.svg.figures.SVGTextFigure"},
 {"id":243, "superclassid":"377", "superclassname":"org.jhotdraw.gui.JDisclosureToolBar", "ownerclassid":"572", "ownerclassname":"org.jhotdraw.samples.svg.gui.AbstractToolBar"},
 {"id":244, "superclassid":"572", "superclassname":"org.jhotdraw.samples.svg.gui.AbstractToolBar", "ownerclassid":"574", "ownerclassname":"org.jhotdraw.samples.svg.gui.ActionsToolBar"},
 {"id":245, "superclassid":"572", "superclassname":"org.jhotdraw.samples.svg.gui.AbstractToolBar", "ownerclassid":"576", "ownerclassname":"org.jhotdraw.samples.svg.gui.AlignToolBar"},
 {"id":246, "superclassid":"572", "superclassname":"org.jhotdraw.samples.svg.gui.AbstractToolBar", "ownerclassid":"578", "ownerclassname":"org.jhotdraw.samples.svg.gui.ArrangeToolBar"},
 {"id":247, "superclassid":"572", "superclassname":"org.jhotdraw.samples.svg.gui.AbstractToolBar", "ownerclassid":"580", "ownerclassname":"org.jhotdraw.samples.svg.gui.CanvasToolBar"},
 {"id":248, "superclassid":"175", "superclassname":"org.jhotdraw.draw.FigureAdapter", "ownerclassid":"583", "ownerclassname":"org.jhotdraw.samples.svg.gui.DrawingComponentRepainter"},
 {"id":249, "superclassid":"572", "superclassname":"org.jhotdraw.samples.svg.gui.AbstractToolBar", "ownerclassid":"585", "ownerclassname":"org.jhotdraw.samples.svg.gui.FigureToolBar"},
 {"id":250, "superclassid":"572", "superclassname":"org.jhotdraw.samples.svg.gui.AbstractToolBar", "ownerclassid":"587", "ownerclassname":"org.jhotdraw.samples.svg.gui.FillToolBar"},
 {"id":251, "superclassid":"572", "superclassname":"org.jhotdraw.samples.svg.gui.AbstractToolBar", "ownerclassid":"589", "ownerclassname":"org.jhotdraw.samples.svg.gui.FontToolBar"},
 {"id":252, "superclassid":"572", "superclassname":"org.jhotdraw.samples.svg.gui.AbstractToolBar", "ownerclassid":"591", "ownerclassname":"org.jhotdraw.samples.svg.gui.LinkToolBar"},
 {"id":253, "superclassid":"572", "superclassname":"org.jhotdraw.samples.svg.gui.AbstractToolBar", "ownerclassid":"598", "ownerclassname":"org.jhotdraw.samples.svg.gui.StrokeToolBar"},
 {"id":254, "superclassid":"572", "superclassname":"org.jhotdraw.samples.svg.gui.AbstractToolBar", "ownerclassid":"602", "ownerclassname":"org.jhotdraw.samples.svg.gui.ToolsToolBar"},
 {"id":255, "superclassid":"572", "superclassname":"org.jhotdraw.samples.svg.gui.AbstractToolBar", "ownerclassid":"604", "ownerclassname":"org.jhotdraw.samples.svg.gui.ViewToolBar"},
 {"id":256, "superclassid":"612", "superclassname":"org.jhotdraw.samples.svg.io.SVGInputFormat", "ownerclassid":"614", "ownerclassname":"org.jhotdraw.samples.svg.io.SVGZInputFormat"},
 {"id":257, "superclassid":"613", "superclassname":"org.jhotdraw.samples.svg.io.SVGOutputFormat", "ownerclassid":"615", "ownerclassname":"org.jhotdraw.samples.svg.io.SVGZOutputFormat"},
 {"id":258, "superclassid":"6", "superclassname":"org.jhotdraw.app.DefaultApplicationModel", "ownerclassid":"620", "ownerclassname":"org.jhotdraw.samples.teddy.TeddyApplicationModel"},
 {"id":259, "superclassid":"2", "superclassname":"org.jhotdraw.app.AbstractView", "ownerclassid":"622", "ownerclassname":"org.jhotdraw.samples.teddy.TeddyView"},
 {"id":260, "superclassid":"19", "superclassname":"org.jhotdraw.app.action.AbstractViewAction", "ownerclassid":"624", "ownerclassname":"org.jhotdraw.samples.teddy.action.ToggleLineNumbersAction"},
 {"id":261, "superclassid":"19", "superclassname":"org.jhotdraw.app.action.AbstractViewAction", "ownerclassid":"625", "ownerclassname":"org.jhotdraw.samples.teddy.action.ToggleLineWrapAction"},
 {"id":262, "superclassid":"19", "superclassname":"org.jhotdraw.app.action.AbstractViewAction", "ownerclassid":"626", "ownerclassname":"org.jhotdraw.samples.teddy.action.ToggleStatusBarAction"},
 {"id":263, "superclassid":"15", "superclassname":"org.jhotdraw.app.View", "ownerclassid":"10", "ownerclassname":"org.jhotdraw.app.DirectoryView"},
 {"id":264, "superclassid":"15", "superclassname":"org.jhotdraw.app.View", "ownerclassid":"12", "ownerclassname":"org.jhotdraw.app.ExportableView"},
 {"id":265, "superclassid":"15", "superclassname":"org.jhotdraw.app.View", "ownerclassid":"14", "ownerclassname":"org.jhotdraw.app.PrintableView"},
 {"id":266, "superclassid":"174", "superclassname":"org.jhotdraw.draw.Figure", "ownerclassid":"136", "ownerclassname":"org.jhotdraw.draw.CompositeFigure"},
 {"id":267, "superclassid":"174", "superclassname":"org.jhotdraw.draw.Figure", "ownerclassid":"142", "ownerclassname":"org.jhotdraw.draw.ConnectionFigure"},
 {"id":268, "superclassid":"652", "superclassname":"org.jhotdraw.xml.DOMStorable", "ownerclassid":"145", "ownerclassname":"org.jhotdraw.draw.Connector"},
 {"id":269, "superclassid":"174", "superclassname":"org.jhotdraw.draw.Figure", "ownerclassid":"150", "ownerclassname":"org.jhotdraw.draw.DecoratedFigure"},
 {"id":270, "superclassid":"262", "superclassname":"org.jhotdraw.draw.Tool", "ownerclassid":"167", "ownerclassname":"org.jhotdraw.draw.DragTracker"},
 {"id":271, "superclassid":"136", "superclassname":"org.jhotdraw.draw.CompositeFigure", "ownerclassid":"168", "ownerclassname":"org.jhotdraw.draw.Drawing"},
 {"id":272, "superclassid":"652", "superclassname":"org.jhotdraw.xml.DOMStorable", "ownerclassid":"168", "ownerclassname":"org.jhotdraw.draw.Drawing"},
 {"id":273, "superclassid":"652", "superclassname":"org.jhotdraw.xml.DOMStorable", "ownerclassid":"174", "ownerclassname":"org.jhotdraw.draw.Figure"},
 {"id":274, "superclassid":"262", "superclassname":"org.jhotdraw.draw.Tool", "ownerclassid":"196", "ownerclassname":"org.jhotdraw.draw.HandleTracker"},
 {"id":275, "superclassid":"174", "superclassname":"org.jhotdraw.draw.Figure", "ownerclassid":"199", "ownerclassname":"org.jhotdraw.draw.ImageHolderFigure"},
 {"id":276, "superclassid":"262", "superclassname":"org.jhotdraw.draw.Tool", "ownerclassid":"247", "ownerclassname":"org.jhotdraw.draw.SelectAreaTracker"},
 {"id":277, "superclassid":"174", "superclassname":"org.jhotdraw.draw.Figure", "ownerclassid":"259", "ownerclassname":"org.jhotdraw.draw.TextHolderFigure"},
 {"id":278, "superclassid":"174", "superclassname":"org.jhotdraw.draw.Figure", "ownerclassid":"511", "ownerclassname":"org.jhotdraw.samples.odg.figures.ODGFigure"},
 {"id":279, "superclassid":"174", "superclassname":"org.jhotdraw.draw.Figure", "ownerclassid":"561", "ownerclassname":"org.jhotdraw.samples.svg.figures.SVGFigure"},
 {"id":280, "superclassid":"15", "superclassname":"org.jhotdraw.app.View", "ownerclassid":"10", "ownerclassname":"org.jhotdraw.app.DirectoryView"},
 {"id":281, "superclassid":"15", "superclassname":"org.jhotdraw.app.View", "ownerclassid":"12", "ownerclassname":"org.jhotdraw.app.ExportableView"},
 {"id":282, "superclassid":"15", "superclassname":"org.jhotdraw.app.View", "ownerclassid":"14", "ownerclassname":"org.jhotdraw.app.PrintableView"},
 {"id":283, "superclassid":"174", "superclassname":"org.jhotdraw.draw.Figure", "ownerclassid":"136", "ownerclassname":"org.jhotdraw.draw.CompositeFigure"},
 {"id":284, "superclassid":"174", "superclassname":"org.jhotdraw.draw.Figure", "ownerclassid":"142", "ownerclassname":"org.jhotdraw.draw.ConnectionFigure"},
 {"id":285, "superclassid":"652", "superclassname":"org.jhotdraw.xml.DOMStorable", "ownerclassid":"145", "ownerclassname":"org.jhotdraw.draw.Connector"},
 {"id":286, "superclassid":"174", "superclassname":"org.jhotdraw.draw.Figure", "ownerclassid":"150", "ownerclassname":"org.jhotdraw.draw.DecoratedFigure"},
 {"id":287, "superclassid":"262", "superclassname":"org.jhotdraw.draw.Tool", "ownerclassid":"167", "ownerclassname":"org.jhotdraw.draw.DragTracker"},
 {"id":288, "superclassid":"136", "superclassname":"org.jhotdraw.draw.CompositeFigure", "ownerclassid":"168", "ownerclassname":"org.jhotdraw.draw.Drawing"},
 {"id":289, "superclassid":"652", "superclassname":"org.jhotdraw.xml.DOMStorable", "ownerclassid":"168", "ownerclassname":"org.jhotdraw.draw.Drawing"},
 {"id":290, "superclassid":"652", "superclassname":"org.jhotdraw.xml.DOMStorable", "ownerclassid":"174", "ownerclassname":"org.jhotdraw.draw.Figure"},
 {"id":291, "superclassid":"262", "superclassname":"org.jhotdraw.draw.Tool", "ownerclassid":"196", "ownerclassname":"org.jhotdraw.draw.HandleTracker"},
 {"id":292, "superclassid":"174", "superclassname":"org.jhotdraw.draw.Figure", "ownerclassid":"199", "ownerclassname":"org.jhotdraw.draw.ImageHolderFigure"},
 {"id":293, "superclassid":"262", "superclassname":"org.jhotdraw.draw.Tool", "ownerclassid":"247", "ownerclassname":"org.jhotdraw.draw.SelectAreaTracker"},
 {"id":294, "superclassid":"174", "superclassname":"org.jhotdraw.draw.Figure", "ownerclassid":"259", "ownerclassname":"org.jhotdraw.draw.TextHolderFigure"},
 {"id":295, "superclassid":"174", "superclassname":"org.jhotdraw.draw.Figure", "ownerclassid":"511", "ownerclassname":"org.jhotdraw.samples.odg.figures.ODGFigure"},
 {"id":296, "superclassid":"174", "superclassname":"org.jhotdraw.draw.Figure", "ownerclassid":"561", "ownerclassname":"org.jhotdraw.samples.svg.figures.SVGFigure"}]